fido/__about__.py
fido/__init__.py
fido/common.py
fido/fido.py
fido-3.0.0.dist-info/DESCRIPTION.rst
fido-3.0.0.dist-info/METADATA
fido-3.0.0.dist-info/RECORD
fido-3.0.0.dist-info/WHEEL
fido-3.0.0.dist-info/metadata.json
fido-3.0.0.dist-info/top_level.txt
