Metadata-Version: 2.0
Name: fido
Version: 3.0.0
Summary: Intelligent asynchronous HTTP client
Home-page: https://github.com/Yelp/fido
Author: John Billings
Author-email: billings@yelp.com
License: Copyright Yelp 2014, All Rights Reserved
Platform: UNKNOWN
Requires-Dist: crochet
Requires-Dist: futures
Requires-Dist: pyOpenSSL
Requires-Dist: service-identity
Requires-Dist: six
Requires-Dist: twisted (>=14.0.0); python_version!="2.6"
Requires-Dist: twisted (>=14.0.0,<15.5); python_version=="2.6"
